my_test/__init__.py
my_test/hello.py
hello_projectA-0.1.0.dist-info/METADATA
hello_projectA-0.1.0.dist-info/WHEEL
hello_projectA-0.1.0.dist-info/top_level.txt
hello_projectA-0.1.0.dist-info/RECORD
