Metadata-Version: 2.1
Name: hello-projectA
Version: 0.1.0
Summary: a test
Home-page: https://github.com/sunzhong0201/my_project
Author: sz
Author-email: usaq1@163.com
Classifier: Programming Language :: Python :: 3
Classifier: License :: OSI Approved :: MIT License
Classifier: Operating System :: OS Independent
Requires-Python: >=3.6
